README.rst
setup.py
scikit_gpuppy.egg-info/PKG-INFO
scikit_gpuppy.egg-info/SOURCES.txt
scikit_gpuppy.egg-info/dependency_links.txt
scikit_gpuppy.egg-info/requires.txt
scikit_gpuppy.egg-info/top_level.txt
skgpuppy/Covariance.py
skgpuppy/FFNI.py
skgpuppy/GaussianProcess.py
skgpuppy/InverseUncertaintyPropagation.py
skgpuppy/MLE.py
skgpuppy/PDF.py
skgpuppy/TaylorPropagation.py
skgpuppy/UncertaintyPropagation.py
skgpuppy/UncertaintyPropagation2.c
skgpuppy/UncertaintyPropagation2.pyx
skgpuppy/Utilities.py
skgpuppy/__init__.py
skgpuppy/tests/__init__.py
skgpuppy/tests/metis_data.py
skgpuppy/tests/tests.py