Metadata-Version: 1.1
Name: scikit-gpuppy
Version: 0.9.3
Summary: Gaussian Process Uncertainty Propagation with PYthon
Home-page: https://github.com/snphbaum/scikit-gpuppy
Author: Philipp Baumgaertel
Author-email: philipp.baumgaertel@fau.de
License: BSD
Keywords: gaussian process kriging random field simulation uncertainty propagation
Platform: UNKNOWN
Classifier: Programming Language :: Python
Classifier: Programming Language :: Python :: 2
Classifier: Programming Language :: Python :: 2.7
Classifier: Programming Language :: Python :: 3
Classifier: Programming Language :: Python :: 3.4
Classifier: Development Status :: 4 - Beta
Classifier: Environment :: Other Environment
Classifier: Intended Audience :: Science/Research
Classifier: License :: OSI Approved :: BSD License
Classifier: Natural Language :: English
Classifier: Operating System :: OS Independent
Classifier: Topic :: Scientific/Engineering :: Mathematics
